{
    "how-to-implement": "",
    "info": {
        "url_png_icon_64x64": "https://raw.githubusercontent.com/CXPA/Pool/master/icon.png",
        "url_png_logo": "https://raw.githubusercontent.com/CXPA/Pool/master/logo.png",
        "location": "",
        "social": {
            "twitter_handle": "CXPA0_Pool",
            "telegram_handle": "CXPA0_StakePool",
            "facebook_handle": "",
            "youtube_handle": "",
            "twitch_handle": "",
            "discord_handle": "",
            "github_handle": ""
        },
        "company": {
            "name": "",
            "addr": "",
            "city": "",
            "country": "",
            "company_id": "",
            "vat_id": ""
        },
        "about": {
            "me": "[CXP₳0] SPO",
            "server": "1 BP 8 vCPU, 16 GB RAM 240 SSD | 1RL 8vCPU 30 GB RAM 200 GB SSD | 1RL 8vCPU 16 GB RAM 240 GB SSD",
            "company": ""
        },
        "rss": ""
    },
    "my-pool-ids": [
        "b78370db9b018cc62683468af3229c53260ddd5025beffbef113f455"
    ],
    "when-satured-then-recommend": [
        ""
    ],
    "telegram-admin-handle": [
        "@CXPA_Pool"
    ],
	"adapools_ext": {
		"prometheus": {
			"0": {
				"name": "",
				"type": "",
				"key": ""
			}
		}
	} 
}
